zfec-1.6.0.1.post0.dist-info/top_level.txt
zfec-1.6.0.1.post0.dist-info/COPYING.TGPPL.rst
zfec-1.6.0.1.post0.dist-info/COPYING.GPL
zfec-1.6.0.1.post0.dist-info/METADATA
zfec-1.6.0.1.post0.dist-info/RECORD
zfec-1.6.0.1.post0.dist-info/entry_points.txt
zfec-1.6.0.1.post0.dist-info/WHEEL
zfec/easyfec.py
zfec/__init__.py
zfec/fec.c
zfec/cmdline_zfec.py
zfec/cmdline_zunfec.py
zfec/fec.h
zfec/_fecmodule.c
zfec/filefec.py
zfec/_version.py
zfec/_fec.cpython-39-i386-linux-gnu.so
zfec/test/__init__.py
zfec/test/test_zfec.py
